cktgym_discovery_server/__init__.py
cktgym_discovery_server/user.py
cktgym_discovery_server/auth/__init__.py
cktgym_discovery_server/auth/provider.py
cktgym_discovery_server/auth/user.py
cktgym_discovery_server/auth/firebase/__init__.py
cktgym_discovery_server/auth/firebase/provider.py
cktgym_discovery_server/authentication/__init__.py
cktgym_discovery_server/authentication/user.py
cktgym_discovery_server/mock/__init__.py
discovery_server/__init__.py
discovery_server/user.py
discovery_server/auth/__init__.py
discovery_server/auth/provider.py
discovery_server/auth/user.py
discovery_server/auth/firebase/__init__.py
discovery_server/auth/firebase/provider.py
discovery_server/authentication/__init__.py
discovery_server/authentication/user.py
discovery_server/mock/__init__.py
cktgym_discovery_server-0.0.4.dist-info/METADATA
cktgym_discovery_server-0.0.4.dist-info/WHEEL
cktgym_discovery_server-0.0.4.dist-info/top_level.txt
cktgym_discovery_server-0.0.4.dist-info/RECORD
